hbm/HumanDimensions.py
hbm/KJointPredictor.py
hbm/OSmplTemplate.py
hbm/OSmplWithPose.py
hbm/Synthesizer.py
hbm/__init__.py
hbm/utils.py
hbm-0.0.1.dist-info/METADATA
hbm-0.0.1.dist-info/WHEEL
hbm-0.0.1.dist-info/top_level.txt
hbm-0.0.1.dist-info/RECORD
