Metadata-Version: 2.1
Name: hbm
Version: 0.0.1
Summary: A rapid prototyping platform focused on modeling realistic human bodies
Home-page: https://github.com/neoglez/hbm
Author: Yansel Gonzalez Tejeda
Author-email: neoglez@gmail.com
Classifier: Programming Language :: Python :: 2
Classifier: Programming Language :: Python :: 3
Classifier: License :: OSI Approved :: MIT License
Classifier: Operating System :: OS Independent
Requires-Dist: numpy
Requires-Dist: opencv-python
